README.md
setup.py
Mishap.egg-info/PKG-INFO
Mishap.egg-info/SOURCES.txt
Mishap.egg-info/dependency_links.txt
Mishap.egg-info/top_level.txt
mishap/__init__.py