Metadata-Version: 1.0
Name: Mishap
Version: 0.1
Summary: For those times when your code is a bit too simple to understand
Home-page: UNKNOWN
Author: Param Thakkar
Author-email: contact@param.me
License: MIT
Platform: UNKNOWN
